Workbook

Sheet Overview
A1: Auto Classifier Benchmarking System: Development Plan
A2: Course of Independent Study 7CS 9281 | Alliance School of Advanced Computing
A4: What you are building
A5: A web app where a user uploads a tabular dataset and picks a target, metrics, time budget and priorities. The system profiles and preprocesses the data, trains ~8 classifiers with cross-validation and hyperparameter tuning, measures Accuracy, Precision, Recall, F1, ROC-AUC plus training and prediction time, ranks models with user-defined weights, recommends one model with an explanation, stores every run in a database, and produces interactive charts and a downloadable report. Novelty to protect: (1) integrated recommendation layer, (2) joint multi-metric + efficiency evaluation, (3) interactive reporting.
A7: Inputs (edit yellow cells)
A8: Project start date (Monday of week 1) | B8: 46300 | D8: Assumption: 5-Oct-2026, the first Monday after this plan was made. Change to your real start; Timeline dates update.
A10: Progress
A11: Area | B11: Done | C11: Total | D11: % complete
A12: Prerequisites | B12: =COUNTIF(Prerequisites!E2:E21,"Done") -> 0 | C12: =COUNTA(Prerequisites!B2:B21) -> 20 | D12: =IF(C12=0,0,B12/C12) -> 0
A13: Dev steps / prompts | B13: =COUNTIF('Steps & Prompts'!J2:J20,"Done") -> 0 | C13: =COUNTA('Steps & Prompts'!A2:A20) -> 19 | D13: =IF(C13=0,0,B13/C13) -> 0
A14: Weekly timeline | B14: =COUNTIF(Timeline!G2:G11,"Done") -> 0 | C14: =COUNTA(Timeline!A2:A11) -> 10 | D14: =IF(C14=0,0,B14/C14) -> 0
A15: Datasets downloaded | B15: =COUNTIF(Datasets!F2:F14,"Yes") -> 0 | C15: =COUNTA(Datasets!B2:B14) -> 13 | D15: =IF(C15=0,0,B15/C15) -> 0
A16: Deliverables & extras | B16: =COUNTIF('Deliverables & Extras'!C2:C13,"Done") -> 0 | C16: =COUNTA('Deliverables & Extras'!B2:B13) -> 12 | D16: =IF(C16=0,0,B16/C16) -> 0
A18: How to use this workbook
A19: 1. Tick off 'Prerequisites' and freeze the 'Decisions' in week 1.
A20: 2. Work through 'Steps & Prompts' in ID order; paste AGENTS.md prompt (0A) first, then one prompt at a time.
A21: 3. Update the Status dropdowns; this page's progress table recalculates automatically.
A22: 4. Yellow cell = input you can edit (start date). Blue text = hardcoded input.
A23: 5. Timeline dates (weeks 1 to 10) are assumptions: stretch or compress to your submission date.

Sheet Prerequisites
A1: Category | B1: Item | C1: Details / recommendation | D1: Owner | E1: Status
A2: Hardware | B2: RAM | C2: Minimum 8 GB; recommended 16 GB | D2: Both | E2: Not started
A3: Hardware | B3: CPU | C3: Minimum 4 cores; recommended 8+ cores (parallel CV and Optuna) | D3: Both | E3: Not started
A4: Hardware | B4: Disk | C4: Minimum 10 GB free; recommended 20 GB (datasets, Docker images, results) | D4: Both | E4: Not started
A5: Hardware | B5: GPU | C5: Not needed (all models are classical) | D5: Both | E5: Not started
A6: Software | B6: Python 3.10 or 3.11 | C6: 3.11 is the safest for all libraries | D6: Both | E6: Not started
A7: Software | B7: Git + GitHub/GitLab account | C7: Private repo; both team members as collaborators | D7: Both | E7: Not started
A8: Software | B8: IDE with AI agent | C8: Cursor, VS Code + Copilot/Claude Code, Windsurf, etc. | D8: Both | E8: Not started
A9: Software | B9: Docker Desktop | C9: For final packaging and PostgreSQL | D9: Both | E9: Not started
A10: Software | B10: PostgreSQL 15+ | C10: Or use SQLite in development and switch later | D10: Both | E10: Not started
A11: Software | B11: Node.js 18+ | C11: Only if you choose React | D11: Both | E11: Not started
A12: Accounts | B12: Kaggle account + API key | C12: Some datasets come from Kaggle | D12: Both | E12: Not started
... A21: Technical trap | B21: Fair timing plan | C21: SVM and KNN explode on large data: per-model timeouts, row sub-sampling rules, failure logging (record failed/timed-out models, do not crash) | D21: Both | E21: Not started

Sheet Decisions
A1: # | B1: Decision | C1: Recommendation | D1: Rationale / notes
A2: 1 | B2: Frontend | C2: FastAPI backend + Streamlit frontend for the MVP | D2: Fastest route to a working demo; matches 'React or Streamlit' on your slide. Add React only if time remains.
A3: 2 | B3: Database | C3: SQLite in development, PostgreSQL in Docker for the final demo | D3: SQLAlchemy makes the switch a config change.
A4: 3 | B4: Hyperparameter search | C4: Optuna (TPE sampler) with a fixed trial budget per model; RandomizedSearchCV as selectable baseline
A5: 4 | B5: Evaluation protocol | C5: Stratified 5-fold CV, fixed random seed, identical folds for all models, held-out test set for final scores
A6: 5 | B6: Multiclass metrics | C6: Macro precision/recall/F1; ROC-AUC with ovr + macro; also report weighted versions
A7: 6 | B7: Timing definition | C7: Training time = wall-clock fit() time; prediction time = seconds per 1,000 rows (median of repeated runs); fix n_jobs for all models and record it
A8: 7 | B8: Ranking method | C8: Weighted sum of min-max normalised scores, plus TOPSIS and a Pareto front as alternatives
A9: 8 | B9: Scope boundary | C9: Tabular classification only (binary and multiclass) | D9: Multilabel and multimodal stay in future work (your limitations slide says they are less mature).

Sheet Timeline
A1: Week | B1: Starts | C1: Ends | D1: Step(s) | E1: Output | F1: Milestone | G1: Status
A2: 1 | B2: =Overview!$B$8+7*(A2-1) -> 46300 | C2: =B2+6 -> 46306 | D2: 0, 1 | E2: Repo, environment, datasets, registry | G2: Not started
A3: 2 | B3: =Overview!$B$8+7*(A3-1) -> 46307 | C3: =B3+6 -> 46313 | D3: 2, 3 | E3: Profiler and leak-free preprocessing | G3: Not started
A4: 3 | B4: =Overview!$B$8+7*(A4-1) -> 46314 | C4: =B4+6 -> 46320 | D4: 4, 5 | E4: Model registry, benchmark engine v1 (CLI works end to end) | G4: Not started
A5: 4 | B5: =Overview!$B$8+7*(A5-1) -> 46321 | C5: =B5+6 -> 46327 | D5: 5 (cont.), 6 | E5: Tuning, timing, metrics aggregation | F5: MILESTONE: `python -m acbs.cli run --dataset adult --target income` prints a ranked table | G5: Not started
A6: 5 | B6: =Overview!$B$8+7*(A6-1) -> 46328 | C6: =B6+6 -> 46334 | D6: 7 | E6: Recommendation engine and explanations | G6: Not started
A7: 6 | B7: =Overview!$B$8+7*(A7-1) -> 46335 | C7: =B7+6 -> 46341 | D7: 8, 9 | E7: Database, visualisations and report | G7: Not started
A8: 7 | B8: =Overview!$B$8+7*(A8-1) -> 46342 | C8: =B8+6 -> 46348 | D8: 10 | E8: REST API | G8: Not started
A9: 8 | B9: =Overview!$B$8+7*(A9-1) -> 46349 | C9: =B9+6 -> 46355 | D9: 11 | E9: Streamlit UI | G9: Not started
A10: 9 | B10: =Overview!$B$8+7*(A10-1) -> 46356 | C10: =B10+6 -> 46362 | D10: 12 | E10: Full experiments, validation, tests | G10: Not started
A11: 10 | B11: =Overview!$B$8+7*(A11-1) -> 46363 | C11: =B11+6 -> 46369 | D11: 13 | E11: Docker, docs, final paper results, demo | G11: Not started

Sheet Steps & Prompts
A1: ID | B1: Step | C1: Title | D1: Week | E1: Owner | F1: Goal | G1: Prompt for | H1: Prompt (copy into IDE agent) | I1: Done when | J1: Status
A2: 0A | B2: 0 | C2: Project scaffold and agent context | D2: 1 | E2: Both | F2: A clean repo, reproducible environment, and a permanent context file for the agent. | G2: Create AGENTS.md (or .cursorrules for Cursor) | H2: Create an AGENTS.md at the repo root describing this project for any AI coding agent. PROJECT: "Auto Classifier Benchmarking System" (package name: acbs). A system that takes a tabular dataset + target column, preprocesses it, trains and tunes multiple classifiers (Logistic Regression, SVM, Decision Tree, Random Forest, XGBoost, Gradient Boosting, Naive Bayes, KNN) with stratified k-fold cross-validation, measures Accuracy, Precision, Recall, F1, ROC-AUC, training time and prediction time, ranks models using user-defined weights, recommends the best model with a textual explanation, stores every experiment in a database, and presents interactive Plotly charts and a downloadable HTML/PDF report via a FastAPI backend and Streamlit frontend. RULES FOR THE AGENT: - Python 3.11, type hints everywhere, docstrings on public functions, ruff-formatted. - Never apply scaling/encoding/imputation/SMOTE outside a sklearn/imblearn Pipeline; all of it must be fit only on training folds (no data leakage). - All randomness goes through a single seed from config (default 42). - All models must be compared on identical CV folds. - Never crash the whole benchmark when one model fails or times out; record status ("ok" | "failed" | "timeout") and the error message and continue. - Config lives in configs/*.yaml, never hardcoded. - Every module gets pytest tests in tests/ mirroring the src structure. - Use logging, not print. - Do not add dependencies without adding them to pyproject.toml. - Keep functions small and pure where possible; business logic must not live in API or UI files. Also include: repo structure (use the tree below), common commands (install, test, lint, run API, run UI), and a "definition of done" checklist for any change. [paste the repository tree from the 'Repo Structure' sheet] | I2: make test passes, CI is green, both teammates can clone and run. | J2: Not started
A3: 0B | B3: 0 | C3: Project scaffold and agent context | D3: 1 | E3: Both | F3: Scaffold the repository. | G3: Scaffold the repository | H3: Read AGENTS.md. Scaffold the repository exactly as described: create all folders with __init__.py files, a pyproject.toml (use hatch or setuptools, package "acbs" under src/), dependencies: scikit-learn, pandas, numpy, scipy, xgboost, imbalanced-learn, optuna, plotly, matplotlib, seaborn, fastapi, uvicorn[standard], pydantic, pydantic-settings, sqlalchemy, alembic, streamlit, pyyaml, jinja2, openml, joblib, typer; dev deps: pytest, pytest-cov, ruff, mypy, pre-commit. Add: .gitignore (data/raw, __pycache__, .venv, *.db), a Makefile with targets install/test/lint/api/ui, a ruff + pre-commit config, a GitHub Actions workflow that runs ruff and pytest, and a minimal CLI entry point `acbs` (typer) with a `version` command. Add one smoke test. Do not implement any business logic yet. Show me the commands to create the venv and run the tests. | I3: make test passes, CI is green, both teammates can clone and run. | J3: Not started
A4: 1 | B4: 1 | C4: Dataset registry and loader | D4: 1 | E4: Both | F4: One consistent way to load any benchmark dataset. | G4: Registry + loader | H4: Implement src/acbs/data/loader.py and data/registry.yaml. 1. registry.yaml: list datasets with fields: name, source ("openml"|"uci"|"kaggle"|"local"), identifier (OpenML id / URL / path), target_column, domain (healthcare|finance|fraud| customer|general), task ("binary"|"multiclass"), and notes. Add entries for: breast_cancer, pima_diabetes, heart_disease, german_credit, bank_marketing, adult, telco_churn, credit_card_fraud, wine_quality, dry_bean, covertype_sample, stroke. Use OpenML ids where they exist. 2. loader.py: - load_dataset(name_or_path, target=None) -> LoadedDataset (dataclass: X: DataFrame, y: Series, meta: dict) with caching to data/processed/ as parquet. - Supports OpenML (via openml package), local CSV/Excel/Parquet uploads, and registry names. - Validates: target exists, at least 2 classes, no all-null columns, minimum 50 rows; raises clear custom exceptions (DatasetError subclasses). - Strips whitespace from column names, parses obvious numeric-as-string columns, encodes the target with LabelEncoder and keeps the mapping in meta. 3. A script scripts/download_datasets.py that downloads everything in the registry. 4. Tests using small in-memory CSVs: valid load, missing target, single-class target, duplicate column names. Do not do any preprocessing here (that is a later step). | I4: download_datasets.py pulls all datasets and load_dataset("adult") returns X, y. | J4: Not started
A5: 2 | B5: 2 | C5: Dataset profiler and meta-features | D5: 2 | E5: Person A | F5: The 'analyzes data characteristics' part of the abstract; feeds explanations later. | G5: Profiler | H5: Implement src/acbs/data/profiler.py. profile_dataset(X, y) -> DatasetProfile (pydantic model, JSON serializable) containing: - n_rows, n_features, n_numeric, n_categorical, n_high_cardinality_categorical (>50 unique) - missing_ratio overall and per column (top 10 worst), n_duplicate_rows - class_distribution (counts and ratios), n_classes, imbalance_ratio (majority/minority), is_imbalanced (ratio > 3 configurable), task_type (binary|multiclass) - numeric stats: skewness summary, share of features with |skew|>1, outlier share (IQR rule) - dimensionality ratio (features/rows), estimated memory MB - size_category: small (<5k rows), medium (5k-100k), large (>100k) - warnings: list of human-readable strings (e.g. "Severe class imbalance 1:577", "3 columns have >40% missing values", "Possible ID column: <name>") Also detect likely ID columns (unique ratio > 0.95 and integer/string) and constant columns, and expose them as `suggested_drop_columns`. Add a function profile_to_dict() and tests on synthetic data (balanced, imbalanced, with missing values, with an ID column). | I5: Profiler returns correct warnings on all four synthetic test cases. | J5: Not started
A6: 3 | B6: 3 | C6: Leak-free preprocessing pipeline | D6: 2 | E6: Person A | F6: Data cleaning, feature engineering and imbalance handling (Data Preprocessing Module). | G6: Preprocessing + imbalance + splitter | H6: Implement src/acbs/preprocessing/pipeline.py and imbalance.py. build_preprocessor(profile, config, model_family) -> sklearn ColumnTransformer: - numeric: SimpleImputer(median) -> optional outlier clipping -> scaler. Scaling is applied only for model families that need it (linear, svm, knn, naive_bayes-gaussian optional); tree-based models (decision tree, RF, GB, XGBoost) skip scaling. - categorical: SimpleImputer(most_frequent) -> OneHotEncoder(handle_unknown="ignore", min_frequency configurable) for cardinality <= 15; for higher cardinality use TargetEncoder (sklearn >= 1.3) or OrdinalEncoder. Make this threshold configurable. - drop ID/constant columns from profile.suggested_drop_columns. - optional feature selection (SelectKBest or variance threshold) controlled by config. imbalance.py: get_imbalance_strategy(profile, config) returns one of "none" | "class_weight" | "smote" | "random_under". Default rule: class_weight when imbalance ratio > 3; SMOTE only if user enables it and minority count >= 6; never SMOTE on datasets above a configurable row limit. build_full_pipeline(model, preprocessor, imbalance_strategy) returns an imblearn.pipeline.Pipeline where SMOTE (if used) is placed AFTER the preprocessor and only runs on training folds. If strategy is class_weight, set class_weight="balanced" on models that support it (and sample_weight handling note for XGBoost via scale_pos_weight). Also create splitter.py with: make_holdout_split (stratified, 80/20) and make_cv_splitter (StratifiedKFold, shuffled, seeded) so every model gets identical folds. Write tests proving: no leakage (fit on train only, via checking transformer statistics), unseen categories at predict time don't crash, tree models get no scaler, SMOTE runs only inside fit. | I6: Leakage, unseen-category, no-scaler-for-trees and SMOTE-in-fit tests all pass. | J6: Not started
A7: 4 | B7: 4 | C7: Model registry and search spaces | D7: 3 | E7: Person A | F7: The 8 algorithms as plug-in components. | G7: Registry + search spaces | H7: Implement src/acbs/models/registry.py, search_spaces.py and configs/search_spaces.yaml. registry.py: - A ModelSpec dataclass: name, family ("linear"|"svm"|"tree"|"ensemble"|"boosting"| "naive_bayes"|"instance"), estimator_factory(params, seed, n_jobs), needs_scaling: bool, supports_class_weight: bool, supports_proba: bool, interpretability_score (1-5), scalability_note, max_rows (optional safety limit, e.g. SVM 20000, KNN 100000). - register 8 models: LogisticRegression, SVC (probability=True; if rows > max_rows use LinearSVC wrapped in CalibratedClassifierCV), DecisionTree, RandomForest, XGBoost, GradientBoosting (sklearn), GaussianNB, KNN. - get_models(names=None) and an easy decorator/function to register extra models later. search_spaces.py + YAML: Optuna search space per model with sensible ranges, e.g. LR: C log-uniform 1e-3..1e2, penalty/solver combos; SVM: C, gamma, kernel (rbf/linear); DT: max_depth, min_samples_split, min_samples_leaf, criterion; RF: n_estimators 100-500, max_depth, max_features, min_samples_leaf; XGB: n_estimators, learning_rate log, max_depth, subsample, colsample_bytree, reg_lambda; GB: n_estimators, learning_rate, max_depth, subsample; NB: var_smoothing log; KNN: n_neighbors, weights, p. Provide suggest_params(trial, model_name) for Optuna AND a RandomizedSearchCV-compatible param_distributions dict from the same definition (single source of truth). Tests: every registered model can fit and predict_proba on a toy dataset, and every search space can be sampled. | I7: All 8 models fit/predict_proba on a toy dataset; all search spaces sample. | J7: Not started
A8: 5A | B8: 5 | C8: Benchmark engine: metrics and timing | D8: 3 | E8: Person A | F8: Metrics and timing for the Evaluation Module. | G8: Metrics + timing | H8: Implement src/acbs/benchmark/metrics.py and timing.py. metrics.py: compute_metrics(y_true, y_pred, y_proba, classes) -> dict with accuracy, precision_macro, recall_macro, f1_macro, precision_weighted, recall_weighted, f1_weighted, roc_auc (binary: roc_auc_score on positive-class proba; multiclass: multi_class="ovr", average="macro"), plus balanced_accuracy and MCC. Handle edge cases: a class missing from a fold (roc_auc -> NaN, not a crash), zero_division=0, models without predict_proba (fall back to decision_function with softmax, flag it). Also provide get_scorers() returning the sklearn scorer dict for cross_validate. timing.py: measure_training_time (context manager using time.perf_counter) and measure_prediction_time(model, X, repeats=5, per=1000) returning median seconds per 1000 rows after one warm-up call. Record n_jobs used. Add unit tests with a dummy estimator using time.sleep to verify timings within tolerance. | I8: Unit tests pass, including the missing-class and sleep-based timing tests. | J8: Not started
A9: 5B | B9: 5 | C9: Benchmark engine: tuning and orchestration (heart of the project) | D9: 3-4 | E9: Person A | F9: The Model Training & Benchmarking Module. | G9: Engine + tuner + CLI | H9: Implement src/acbs/benchmark/engine.py and tuner.py. BenchmarkConfig (pydantic): models list, cv_folds=5, seed, metrics_primary="f1_macro", tuning ("none"|"optuna"|"random"), n_trials per model (default 20), time_budget_seconds per model (default 300) and total budget, n_jobs, imbalance_strategy override, test_size. tuner.py: tune_model(model_spec, X_train, y_train, preprocessor_factory, cfg) -> best_params, trials_history. Use Optuna TPE (seeded), optimize the primary metric via cross_val_score on the SAME CV splitter, enforce a timeout, and use a MedianPruner where applicable. Provide the RandomizedSearchCV alternative behind the same interface. engine.py: run_benchmark(dataset: LoadedDataset, cfg, progress_callback=None) -> BenchmarkResult: 1. profile the dataset; hold-out split. 2. for each model: build the full pipeline, tune (if enabled) on train only, then run cross_validate with return_train_score=False on the training set to get per-fold metrics and fit_time, then refit on full train, evaluate on the hold-out test set, and measure final training time and prediction time (per 1000 rows). 3. Wrap each model in try/except + timeout (use a subprocess/joblib timeout or Optuna timeout + a guard); on failure store status and error and continue. 4. Skip or subsample models that exceed ModelSpec.max_rows, and record that decision in a "notes" field (never silently). 5. Call progress_callback(model_name, step, total, message) so the UI can show progress. 6. Return per-model: cv mean/std for every metric, test metrics, training_time, prediction_time_per_1k, best_params, status, notes, plus dataset profile and config (for reproducibility). Include library versions and seed in the result. Parallelism: run folds in parallel with n_jobs but keep models sequential so that timings are comparable. Document this decision in a docstring. Add a CLI command `acbs run --dataset adult --target income --models all --tuning optuna` that prints a results table (use rich or tabulate). Tests: run the engine on a small synthetic dataset with 3 fast models and tuning="none"; check result structure, determinism with the same seed, and that a deliberately broken model gets status="failed" without stopping the run. | I9: CLI produces a results table on Adult in reasonable time; results identical across two runs with the same seed. | J9: Not started
A10: 6 | B10: 6 | C10: Results aggregation and statistical comparison | D10: 4 | E10: Person A | F10: Make the comparison scientifically defensible. | G10: Aggregation + stats tests | H10: Implement src/acbs/benchmark/aggregate.py. - results_to_dataframe(BenchmarkResult) -> tidy DataFrame, one row per model. - Per-fold score matrix extraction for statistical tests. - compare_models_statistically(fold_scores): Friedman test across models when >= 3 models and >= 5 folds is not enough power, so also provide pairwise corrected resampled t-test (Nadeau-Bengio) and a Wilcoxon signed-rank fallback; return p-values and a flag "statistically_tied_with_best". - For multi-dataset experiments (used later in step 12): compute average rank per model across datasets and a Nemenyi/critical-difference style summary. - rank_by_metric(df, metric) with ties handled by average rank. Tests with synthetic fold scores where one model is clearly better and where two are tied. | I10: Tests pass for the clear-winner and tied-models synthetic cases. | J10: Not started
A11: 7 | B11: 7 | C11: Recommendation engine (main novelty) | D11: 5 | E11: Person A | F11: Turn numbers into 'use model X, because...'. | G11: Scoring + explanation | H11: Implement src/acbs/recommend/scoring.py and explain.py. UserPreferences (pydantic): weights for accuracy/f1/precision/recall/roc_auc/train_time/ predict_time/interpretability (non-negative, auto-normalised to sum 1), constraints (max_training_time_s, max_prediction_time_ms_per_1k, min_recall, min_precision), method ("weighted_sum"|"topsis"), preset ("balanced"|"max_accuracy"|"fast_inference"| "interpretable"|"imbalance_safe" where imbalance_safe emphasises recall and F1). scoring.py: - normalize(): min-max for benefit metrics, inverted min-max for cost metrics (time), use log-scale for time before normalising so one very slow model doesn't flatten the rest. - score_models(results_df, prefs) -> DataFrame with a composite score and rank; apply hard constraints first (violating models are marked "excluded" with the reason). - TOPSIS implementation as an alternative. - pareto_front(results_df, x="training_time", y="f1_macro") returns the non-dominated models. - sensitivity_analysis(results_df, prefs): perturb weights +-20% repeatedly and report how often each model stays rank 1 (a "recommendation stability" percentage). explain.py: generate_explanation(rec, results_df, profile, prefs) -> structured object with a headline ("Recommended: XGBoost"), a 3-5 sentence plain-English reason built from templates (strongest metrics vs runner-up, time trade-offs, whether it is statistically tied with the runner-up, stability %), caveats (e.g. "Dataset is highly imbalanced; accuracy is misleading, ranking emphasised F1"), and a "why not" line for 2 other models. Use deterministic templates, NOT an LLM, so results are reproducible. Tests: changing weights from accuracy to speed changes the winner on a crafted results table; constraints exclude models; the Pareto front is correct on a hand-made example. | I11: Weight changes flip the winner on the crafted table; constraints exclude models; Pareto front correct. | J11: Not started
A12: 8 | B12: 8 | C12: Experiment tracking database | D12: 6 | E12: Person B | F12: Persistent storage (PostgreSQL/MySQL on your slide). | G12: SQLAlchemy models + repository | H12: Implement src/acbs/storage/models.py and repository.py with SQLAlchemy 2.0 and Alembic. Tables: datasets (id, name, source, n_rows, n_features, profile_json, file_hash, created_at), experiments (id, dataset_id, config_json, preferences_json, status, started_at, finished_at, seed, lib_versions_json), model_runs (id, experiment_id, model_name, status, error, notes, cv_metrics_json, test_metrics_json, training_time, prediction_time_per_1k, best_params_json, fold_scores_json), recommendations (id, experiment_id, model_name, score_table_json, explanation_json, stability_pct). Use SQLite by default and a DATABASE_URL env var for PostgreSQL. Provide a Repository class with: create_experiment, update_status, save_results, save_recommendation, get_experiment, list_experiments(filters), delete_experiment, and load_result_as_dataframe. Create the first Alembic migration. Dedupe uploaded datasets by file hash. Write tests against an in-memory SQLite database. No business logic in this layer. | I12: Repository tests pass on in-memory SQLite; migration applies cleanly. | J12: Not started
... A20: 13B | B20: 13 | C20: Documentation | D20: 10 | E20: Both | F20: Final documentation. | G20: README + docs | H20: Write README.md (overview, architecture diagram in mermaid matching our modules, quick start with and without Docker, CLI examples, configuration reference, how to add a new model, how the recommendation scoring works, limitations), docs/architecture.md, docs/api.md (generated from the OpenAPI schema), and docs/reproducibility.md. Add a CITATION-style note. Include a "Known limitations" section: tabular classification only, hold-out size, timing depends on hardware, no multilabel/multimodal support. | I20: README, architecture, API and reproducibility docs complete. | J20: Not started

Sheet Datasets
A1: Domain | B1: Dataset | C1: Source | D1: Task | E1: Why it is useful | F1: Downloaded?
A2: Healthcare | B2: Breast Cancer Wisconsin | C2: UCI / OpenML | D2: Binary | E2: Small, clean | F2: No
A3: Healthcare | B3: Pima Indians Diabetes | C3: UCI / OpenML | D3: Binary | E3: Small, missing-as-zero values | F3: No
A4: Healthcare | B4: Heart Disease | C4: UCI | D4: Binary | E4: Small, mixed types | F4: No
A5: Healthcare (imbalanced) | B5: Stroke Prediction | C5: Kaggle | D5: Binary | E5: Strong class imbalance | F5: No
A6: Finance | B6: German Credit | C6: UCI / OpenML | D6: Binary | E6: Mixed numeric/categorical | F6: No
A7: Finance | B7: Bank Marketing | C7: UCI | D7: Binary | E7: Mixed numeric/categorical, imbalanced | F7: No
A8: Finance | B8: Adult / Census Income | C8: UCI / OpenML | D8: Binary | E8: Mixed types; used for the week-4 milestone | F8: No
A9: Fraud | B9: Credit Card Fraud (284k rows, 0.17% fraud) | C9: Kaggle | D9: Binary | E9: Extreme imbalance, large | F9: No
A10: Customer analytics | B10: Telco Customer Churn | C10: Kaggle | D10: Binary | E10: Categorical heavy | F10: No
A11: Multiclass | B11: Wine Quality | C11: UCI | D11: Multiclass | E11: Multiclass | F11: No
A12: Multiclass | B12: Dry Bean | C12: UCI | D12: Multiclass | E12: Multiclass | F12: No
... A14: Multiclass | B14: Letter Recognition | C14: UCI / OpenML | D14: Multiclass | E14: Many classes | F14: No

Sheet Risks
A1: Risk | B1: Mitigation
A2: Benchmark takes too long (SVM/KNN on large data) | B2: Per-model timeout, max_rows rule, sub-sampling note, 20 Optuna trials default, 'quick mode' for demos
A3: Inflated scores from leakage | B3: Pipelines only; leakage test in Step 3
A4: Agent writes huge, unfocused code | B4: One step per prompt, 'only implement listed files', commit after every step
A5: Results not reproducible | B5: Single seed, stored config and library versions, identical folds
A6: Streamlit feels slow when rerunning | B6: Cache API results with st.cache_data; use /rerank instead of retraining
A7: Scope creep (deep learning, multilabel, NLP) | B7: Keep in Future Work; your own slide lists them as limitations
A8: Timings noisy | B8: Median of repeats, warm-up call, fixed n_jobs, close other apps while running experiments

Sheet Deliverables & Extras
A1: Type | B1: Item | C1: Status
A2: Final deliverable | B2: Working demo (Docker or local) with 2 prepared datasets for the live demo | C2: Not started
A3: Final deliverable | B3: Source repo with README and tests passing in CI | C3: Not started
A4: Final deliverable | B4: Results tables and figures from Step 12 | C4: Not started
A5: Final deliverable | B5: Updated paper: add Methodology, Implementation, Results, Discussion, Conclusion, Future Work (draft currently has Abstract, Introduction, References only) | C5: Not started
A6: Final deliverable | B6: Demo video (3 to 5 minutes) as backup for live-demo failure | C6: Not started
A7: Final deliverable | B7: Final presentation slides (fill the empty 'Project work plan and timeline' slide from the Timeline sheet) | C7: Not started
A8: Optional extension | B8: Meta-learning recommender: predict a good model from dataset meta-features before training everything (refs [5], [14]) | C8: Not started
A9: Optional extension | B9: SHAP-based explanations for the recommended model | C9: Not started
A10: Optional extension | B10: Regression support (same architecture) | C10: Not started
A11: Optional extension | B11: Authentication and multi-user workspaces | C11: Not started
A12: Optional extension | B12: React frontend replacing Streamlit | C12: Not started
A13: Optional extension | B13: Threshold tuning for imbalanced datasets (cost-sensitive decision threshold) | C13: Not started

Sheet Repo Structure
A1: Suggested repository structure
A3: auto-classifier-benchmark/
A4: ├── AGENTS.md # master context for the IDE agent (Step 0)
A5: ├── pyproject.toml
A6: ├── docker-compose.yml
A7: ├── configs/
A8: │ ├── default.yaml # models, metrics, CV folds, budgets
A9: │ └── search_spaces.yaml
A10: ├── data/
A11: │ ├── raw/ processed/ registry.yaml
A12: ├── src/acbs/
A13: │ ├── data/ loader.py, profiler.py, splitter.py
... A25: └── docs/

Sheet Working Tips
A1: Working method with an IDE agent
A3: 1 | B3: Always start a session with: "Read AGENTS.md and the files in src/acbs/<module> first."
A4: 2 | B4: One prompt = one module. Review the diff before accepting. Run tests yourself.
A5: 3 | B5: If something fails, paste the FULL error and the failing test back, not a summary.
A6: 4 | B6: After each step ask: "Review the code you just wrote for data leakage, unhandled exceptions, hardcoded values, and missing tests. List issues, then fix them."
A7: 5 | B7: Keep a docs/decisions.md log; it becomes raw material for the Methodology section of your paper.
A8: 6 | B8: Commit per step with clear messages, e.g. feat(benchmark): add metrics and timing.
A9: 7 | B9: If the agent produces too much, say: "Only implement the files listed. Do not add extra features."
